pytest_soft_asserts/__init__.py
pytest_soft_asserts/exceptions.py
pytest_soft_asserts/plugin.py
pytest_soft_asserts/table.py
pytest_soft_asserts/transformer.py
pytest_soft_asserts/libassert/__init__.py
pytest_soft_asserts/libassert/lib.py
pytest_soft_asserts/libassert/models.py
pytest_soft_assertions-0.1.2.dist-info/METADATA
pytest_soft_assertions-0.1.2.dist-info/WHEEL
pytest_soft_assertions-0.1.2.dist-info/entry_points.txt
pytest_soft_assertions-0.1.2.dist-info/top_level.txt
pytest_soft_assertions-0.1.2.dist-info/RECORD
