Metadata-Version: 2.1
Name: pytest-soft-assertions
Version: 0.1.2
Summary: UNKNOWN
Home-page: UNKNOWN
Author: okorolev
Author-email: johnnyprobel@gmail.com
License: UNKNOWN
Project-URL: Source, https://github.com/okorolev/pytest-soft-assertions
Keywords: pytest,ast,soft-asserts,asserts,testing,debug
Platform: UNKNOWN
Classifier: Framework :: Pytest
Classifier: Programming Language :: Python :: 3
Classifier: Development Status :: 3 - Alpha
